agxclick/__init__.py
agxclick/agx_application.py
agxclick/application_step_listener.py
agxclick/brick_reader.py
agxclick/brick_utils.py
agxclick/click_application.py
agxclick/click_event_listener.py
agxclick/click_robot.py
agxclick/graphics_throttler.py
agxclick/keyboard_listener.py
agxclick/message_factory.py
agxclick/reset_batch_listener.py
agxclick/wallclock.py
agxclick-0.4.1.dist-info/METADATA
agxclick-0.4.1.dist-info/WHEEL
agxclick-0.4.1.dist-info/RECORD
