Metadata-Version: 2.1
Name: agxclick
Version: 0.4.1
Summary: Controller to AGX Dynamics communication using pclick messaging
Home-page: https://github.com/algoryx/click-mirror
License: Apache-2.0
Author: Algoryx Simulation
Author-email: contact@algoryx.se
Requires-Python: >=3.8
Classifier: License :: OSI Approved :: Apache Software License
Classifier: Programming Language :: Python :: 3
Classifier: Programming Language :: Python :: 3.8
Classifier: Programming Language :: Python :: 3.9
Classifier: Programming Language :: Python :: 3.10
Classifier: Programming Language :: Python :: 3.11
Classifier: Programming Language :: Python :: 3.12
Requires-Dist: agxBrick (>=0.6.0)
Requires-Dist: pclick (>=0.4.1)
Project-URL: Repository, https://github.com/algoryx/click-mirror
